{
  "template": "sections/categories.jinja",
  "name": {
    "ar": "التصنيفات",
    "en": "Categories"
  },
  "settings": [
    {
      "id": "title_ar",
      "type": "text",
      "label": {
        "ar": "العنوان (عربي)",
        "en": "Title (Arabic)"
      },
      "default": "اكتشف مجموعاتنا المميزة"
    },
    {
      "id": "title_en",
      "type": "text",
      "label": {
        "ar": "العنوان (إنجليزي)",
        "en": "Title (English)"
      },
      "default": "Discover our signature collections"
    },
    {
      "id": "categories",
      "type": "list",
      "label": {
        "ar": "التصنيفات",
        "en": "Categories"
      },
      "max_items": 12,
      "settings": [
        {
          "id": "category",
          "type": "category",
          "label": {
            "ar": "اختر التصنيف",
            "en": "Select category"
          }
        }
      ]
    },
    {
      "id": "more_text_ar",
      "type": "text",
      "label": {
        "ar": "نص زر جميع التصنيفات (عربي)",
        "en": "View all button text (Arabic)"
      },
      "default": "عرض الكل"
    },
    {
      "id": "more_text_en",
      "type": "text",
      "label": {
        "ar": "نص زر جميع التصنيفات (إنجليزي)",
        "en": "View all button text (English)"
      },
      "default": "View all"
    },
    {
      "id": "display_more",
      "type": "checkbox",
      "label": {
        "ar": "عرض زر جميع التصنيفات",
        "en": "Display view all button"
      },
      "default": false
    }
  ]
}